{"cameraMode":{"drawMode":0,"name":"Shaded","section":"Shading Mode"},"sceneLighting":false,"audioPlay":false,"sceneViewState":{"m_AlwaysRefresh":false,"showFog":true,"showSkybox":false,"showFlares":true,"showImageEffects":true,"showParticleSystems":true,"showVisualEffectGraphs":true,"m_FxEnabled":true},"in2DMode":false,"pivot":{"x":1.6709964275360108,"y":1.1481902599334717,"z":0.1693868488073349},"rotation":{"x":0.15760499238967896,"y":-0.4176674485206604,"z":0.0737883523106575,"w":0.8918333649635315},"size":0.03821919485926628,"orthographic":false}